raptor_pkg/__init__.py
raptor_pkg/raptor-config.py
raptor_pkg/raptor.py
raptor_totp-0.0.1.dist-info/LICENSE
raptor_totp-0.0.1.dist-info/METADATA
raptor_totp-0.0.1.dist-info/WHEEL
raptor_totp-0.0.1.dist-info/top_level.txt
raptor_totp-0.0.1.dist-info/RECORD
