Metadata-Version: 2.1
Name: raptor-totp
Version: 0.0.1
Summary: Raptor, reeve time-based one time password ahead rapidly
Home-page: https://bgi-tumour.oss-cn-hangzhou.aliyuncs.com/code/skip_totp/raptor.py
Author-email: zhoujianwen@aliyun.com
License: UNKNOWN
Platform: UNKNOWN
Requires-Python: >=3.6
